dropclust/__init__.py
dropclust/__main__.py
dropclust/core.py
dropclust/dynamics.py
dropclust/gpu.py
dropclust/iiio.py
dropclust/logger.py
dropclust/metrics.py
dropclust/models.py
dropclust/plot.py
dropclust/resnet_torch.py
dropclust/transforms.py
dropclust/utils.py
dropclust/gui/__init__.py
dropclust/gui/detection.py
dropclust/gui/features.py
dropclust/gui/gui.py
dropclust/gui/gui_components.py
dropclust/gui/iio.py
dropclust/gui/menus.py
dropclust/gui/methods.py
dropclust/gui/symmetry.py
dropclust-0.0.6.dist-info/METADATA
dropclust-0.0.6.dist-info/WHEEL
dropclust-0.0.6.dist-info/entry_points.txt
dropclust-0.0.6.dist-info/top_level.txt
dropclust-0.0.6.dist-info/RECORD
