Metadata-Version: 2.4
Name: dropclust
Version: 0.0.6
Summary: A microscopical image and video platform applied to the analysis of levitating droplet clusters
Home-page: https://gitlab.com/MeLlamoArroz/DropClustGUI
Author: Israel Huaman
Author-email: ihuaman@itmo.ru
License: BSD
Classifier: Programming Language :: Python :: 3
Classifier: License :: OSI Approved :: BSD License
Classifier: Operating System :: OS Independent
Requires-Dist: numpy<2.1,>=1.20.0
Requires-Dist: pandas
Requires-Dist: matplotlib
Requires-Dist: scipy
Requires-Dist: natsort
Requires-Dist: tifffile
Requires-Dist: tqdm
Requires-Dist: numba>=0.53.0
Requires-Dist: llvmlite
Requires-Dist: opencv-python
Requires-Dist: fastremap
Requires-Dist: Cython
Requires-Dist: imagecodecs
Requires-Dist: roifile
Provides-Extra: gui
Requires-Dist: pyqtgraph>=0.11.0rc0; extra == "gui"
Requires-Dist: qtpy; extra == "gui"
Requires-Dist: superqt; extra == "gui"
Requires-Dist: diplib; extra == "gui"
Requires-Dist: Pillow; extra == "gui"
Requires-Dist: pyqt5; extra == "gui"
Requires-Dist: pyqt5.sip; extra == "gui"
Provides-Extra: distributed
Requires-Dist: dask; extra == "distributed"
Requires-Dist: distributed; extra == "distributed"
Requires-Dist: dask_image; extra == "distributed"
Requires-Dist: pyyaml; extra == "distributed"
Requires-Dist: zarr; extra == "distributed"
Requires-Dist: dask_jobqueue; extra == "distributed"
Requires-Dist: bokeh; extra == "distributed"
Provides-Extra: bioimageio
Requires-Dist: bioimageio.core; extra == "bioimageio"
Provides-Extra: all
Requires-Dist: pyqtgraph>=0.11.0rc0; extra == "all"
Requires-Dist: qtpy; extra == "all"
Requires-Dist: superqt; extra == "all"
Requires-Dist: diplib; extra == "all"
Requires-Dist: Pillow; extra == "all"
Requires-Dist: pyqt5; extra == "all"
Requires-Dist: pyqt5.sip; extra == "all"
Requires-Dist: dask; extra == "all"
Requires-Dist: distributed; extra == "all"
Requires-Dist: dask_image; extra == "all"
Requires-Dist: pyyaml; extra == "all"
Requires-Dist: zarr; extra == "all"
Requires-Dist: dask_jobqueue; extra == "all"
Requires-Dist: bokeh; extra == "all"
Requires-Dist: nd2; extra == "all"
Requires-Dist: pynrrd; extra == "all"
Requires-Dist: bioimageio.core; extra == "all"
Dynamic: author
Dynamic: author-email
Dynamic: classifier
Dynamic: description
Dynamic: description-content-type
Dynamic: home-page
Dynamic: license
Dynamic: provides-extra
Dynamic: requires-dist
Dynamic: summary
